gswarm/__init__.py
gswarm/__main__.py
gswarm/cli.py
gswarm/client_resilient.py
gswarm/client/__init__.py
gswarm/client/cli.py
gswarm/data/__init__.py
gswarm/data/cli.py
gswarm/data/pool.py
gswarm/host/__init__.py
gswarm/host/cli.py
gswarm/model/__init__.py
gswarm/model/__main__.py
gswarm/model/cli.py
gswarm/model/fastapi_client.py
gswarm/model/fastapi_head.py
gswarm/model/fastapi_models.py
gswarm/model/http_api.py
gswarm/model/models.py
gswarm/profiler/__init__.py
gswarm/profiler/__main__.py
gswarm/profiler/adaptive_sampler.py
gswarm/profiler/cli.py
gswarm/profiler/client.py
gswarm/profiler/client_common.py
gswarm/profiler/client_grpc.py
gswarm/profiler/client_resilient.py
gswarm/profiler/fix_imports.py
gswarm/profiler/generate_grpc.py
gswarm/profiler/head.py
gswarm/profiler/head_common.py
gswarm/profiler/http_api.py
gswarm/profiler/persistence.py
gswarm/profiler/plot.py
gswarm/profiler/profiler.proto
gswarm/profiler/profiler_pb2.py
gswarm/profiler/profiler_pb2_grpc.py
gswarm/profiler/session_manager.py
gswarm/profiler/stat.py
gswarm/queue/__init__.py
gswarm/queue/cli.py
gswarm/queue/manager.py
gswarm/utils/__init__.py
gswarm/utils/cache.py
gswarm/utils/config.py
gswarm/utils/connection_info.py
gswarm/utils/daemonizer.py
gswarm/utils/draw_metrics.py
gswarm/utils/service_discovery.py
gswarm-0.4.3.dist-info/METADATA
gswarm-0.4.3.dist-info/WHEEL
gswarm-0.4.3.dist-info/entry_points.txt
gswarm-0.4.3.dist-info/RECORD
