Metadata-Version: 2.4
Name: gswarm
Version: 0.4.3
Summary: Distributed GPU cluster management system with profiling and model orchestration
Author-email: Chivier Humber <chivier.humber@outlook.com>, cydia2001 <cydia2001@duck.com>
Requires-Python: >=3.9
Requires-Dist: aiofiles>=23.1.0
Requires-Dist: aiohttp<4.0.0,>=3.9.0
Requires-Dist: aioredis<3.0.0,>=2.0.0
Requires-Dist: fastapi<1.0.0,>=0.100.0
Requires-Dist: grpcio-tools<2.0.0,>=1.60.0
Requires-Dist: grpcio<2.0.0,>=1.60.0
Requires-Dist: httpx<1.0.0,>=0.24.0
Requires-Dist: loguru>=0.7.0
Requires-Dist: matplotlib<4.0.0,>=3.7.0
Requires-Dist: numpy<2.0.0,>=1.24.0
Requires-Dist: nvitop>=1.3.0
Requires-Dist: protobuf<6.0.0,>=5.0.0
Requires-Dist: psutil>=5.9.0
Requires-Dist: pydantic<3.0.0,>=2.0.0
Requires-Dist: python-multipart>=0.0.18
Requires-Dist: pyyaml>=6.0.0
Requires-Dist: requests<3.0.0,>=2.31.0
Requires-Dist: rich<15.0.0,>=13.0.0
Requires-Dist: seaborn>=0.13.2
Requires-Dist: torch>=2.7.0
Requires-Dist: transformers>=4.52.4
Requires-Dist: typer<1.0.0,>=0.9.0
Requires-Dist: uvicorn[standard]<1.0.0,>=0.23.0
Provides-Extra: dev
Requires-Dist: black<25.0.0,>=23.0.0; extra == 'dev'
Requires-Dist: mypy<2.0.0,>=1.0.0; extra == 'dev'
Requires-Dist: pytest-asyncio<1.0.0,>=0.21.0; extra == 'dev'
Requires-Dist: pytest-cov<5.0.0,>=4.0.0; extra == 'dev'
Requires-Dist: pytest<8.0.0,>=7.0.0; extra == 'dev'
Requires-Dist: ruff<1.0.0,>=0.1.0; extra == 'dev'
Provides-Extra: vllm
Requires-Dist: accelerate>=0.24.0; extra == 'vllm'
Requires-Dist: torch>=2.1.0; extra == 'vllm'
Requires-Dist: torchvision>=0.16.0; extra == 'vllm'
Requires-Dist: transformers>=4.44.0; extra == 'vllm'
Requires-Dist: vllm<0.10.0,>=0.9.0; extra == 'vllm'
